[
  {
    "abhaId": "38109629606851",
    "bloodGroup": "O+",
    "diagnosis": "Diagnosis_d276826d",
    "dob": "1992-03-09",
    "fullName": "Recipient_6fffa8",
    "gender": "Male",
    "hospitalId": "H-434",
    "organRequired": "Liver",
    "registeredAt": "2026-01-30T21:51:21.787841",
    "status": "active",
    "submissionType": "backend-api",
    "test_liver_ct": "3",
    "test_liver_ct_date": "2026-01-08",
    "test_liver_echo": "10",
    "test_liver_echo_date": "2026-01-26",
    "test_liver_pftsTest": "6",
    "test_liver_pftsTest_date": "2026-01-14",
    "test_liver_xray": "9",
    "test_liver_xray_date": "2026-01-07",
    "urgencyStatus": "Critical (ICU)"
  },
  {
    "abhaId": "78181356076755",
    "bloodGroup": "O+",
    "diagnosis": "Diagnosis_02eb4d0f",
    "dob": "1968-03-29",
    "fullName": "Recipient_a455a3",
    "gender": "Female",
    "hospitalId": "H-169",
    "organRequired": "Kidney",
    "registeredAt": "2026-01-30T21:51:21.788231",
    "status": "active",
    "submissionType": "backend-api",
    "test_kidney_ct": "1",
    "test_kidney_ct_date": "2026-01-23",
    "test_kidney_echo": "5",
    "test_kidney_echo_date": "2026-01-04",
    "test_kidney_pftsTest": "10",
    "test_kidney_pftsTest_date": "2026-01-09",
    "test_kidney_xray": "8",
    "test_kidney_xray_date": "2026-01-28",
    "urgencyStatus": "Moderate"
  },
  {
    "abhaId": "30365127896685",
    "bloodGroup": "AB+",
    "diagnosis": "Diagnosis_4b2bcbac",
    "dob": "1964-08-12",
    "fullName": "Recipient_dc1b80",
    "gender": "Male",
    "hospitalId": "H-385",
    "organRequired": "Kidney",
    "registeredAt": "2026-01-30T21:51:21.788272",
    "status": "active",
    "submissionType": "backend-api",
    "test_kidney_ct": "9",
    "test_kidney_ct_date": "2026-01-08",
    "test_kidney_echo": "6",
    "test_kidney_echo_date": "2026-01-25",
    "test_kidney_pftsTest": "4",
    "test_kidney_pftsTest_date": "2026-01-15",
    "test_kidney_xray": "1",
    "test_kidney_xray_date": "2026-01-03",
    "urgencyStatus": "Moderate"
  },
  {
    "abhaId": "94041776831183",
    "bloodGroup": "O+",
    "diagnosis": "Diagnosis_d23292ed",
    "dob": "1960-10-07",
    "fullName": "Recipient_3b075e",
    "gender": "Female",
    "hospitalId": "H-826",
    "organRequired": "Heart",
    "registeredAt": "2026-01-30T21:51:21.788307",
    "status": "active",
    "submissionType": "backend-api",
    "test_heart_ct": "6",
    "test_heart_ct_date": "2026-01-19",
    "test_heart_echo": "3",
    "test_heart_echo_date": "2026-01-01",
    "test_heart_pftsTest": "8",
    "test_heart_pftsTest_date": "2026-01-12",
    "test_heart_xray": "1",
    "test_heart_xray_date": "2026-01-03",
    "urgencyStatus": "Urgent (Hospitalized)"
  },
  {
    "abhaId": "44798285044569",
    "bloodGroup": "O+",
    "diagnosis": "Diagnosis_dbf6163b",
    "dob": "1983-12-30",
    "fullName": "Recipient_861115",
    "gender": "Male",
    "hospitalId": "H-177",
    "organRequired": "Lungs",
    "registeredAt": "2026-01-30T21:51:21.788363",
    "status": "active",
    "submissionType": "backend-api",
    "test_lungs_ct": "3",
    "test_lungs_ct_date": "2026-01-23",
    "test_lungs_echo": "5",
    "test_lungs_echo_date": "2026-01-13",
    "test_lungs_pftsTest": "8",
    "test_lungs_pftsTest_date": "2025-12-31",
    "test_lungs_xray": "8",
    "test_lungs_xray_date": "2026-01-07",
    "urgencyStatus": "Critical (ICU)"
  },
  {
    "abhaId": "72736545751156",
    "bloodGroup": "AB-",
    "diagnosis": "Diagnosis_0258e6ab",
    "dob": "2006-11-19",
    "fullName": "Recipient_4f5f06",
    "gender": "Male",
    "hospitalId": "H-224",
    "organRequired": "Liver",
    "registeredAt": "2026-01-30T21:51:21.788402",
    "status": "active",
    "submissionType": "backend-api",
    "test_liver_ct": "9",
    "test_liver_ct_date": "2026-01-09",
    "test_liver_echo": "6",
    "test_liver_echo_date": "2026-01-14",
    "test_liver_pftsTest": "5",
    "test_liver_pftsTest_date": "2026-01-21",
    "test_liver_xray": "8",
    "test_liver_xray_date": "2026-01-26",
    "urgencyStatus": "Stable"
  },
  {
    "abhaId": "14268765359087",
    "bloodGroup": "A+",
    "diagnosis": "Diagnosis_343c2ba2",
    "dob": "1980-12-07",
    "fullName": "Recipient_c311a6",
    "gender": "Male",
    "hospitalId": "H-102",
    "organRequired": "Kidney",
    "registeredAt": "2026-01-30T21:51:21.788438",
    "status": "active",
    "submissionType": "backend-api",
    "test_kidney_ct": "5",
    "test_kidney_ct_date": "2026-01-17",
    "test_kidney_echo": "4",
    "test_kidney_echo_date": "2026-01-14",
    "test_kidney_pftsTest": "3",
    "test_kidney_pftsTest_date": "2026-01-15",
    "test_kidney_xray": "5",
    "test_kidney_xray_date": "2026-01-22",
    "urgencyStatus": "Stable"
  },
  {
    "abhaId": "57583085633664",
    "bloodGroup": "A-",
    "diagnosis": "Diagnosis_ea0812aa",
    "dob": "1988-09-21",
    "fullName": "Recipient_469c9e",
    "gender": "Male",
    "hospitalId": "H-528",
    "organRequired": "Lungs",
    "registeredAt": "2026-01-30T21:51:21.788478",
    "status": "active",
    "submissionType": "backend-api",
    "test_lungs_ct": "10",
    "test_lungs_ct_date": "2026-01-13",
    "test_lungs_echo": "7",
    "test_lungs_echo_date": "2026-01-03",
    "test_lungs_pftsTest": "6",
    "test_lungs_pftsTest_date": "2026-01-16",
    "test_lungs_xray": "9",
    "test_lungs_xray_date": "2026-01-01",
    "urgencyStatus": "Critical (ICU)"
  },
  {
    "abhaId": "37579992875624",
    "bloodGroup": "O+",
    "diagnosis": "Diagnosis_9aabe186",
    "dob": "1997-11-09",
    "fullName": "Recipient_112398",
    "gender": "Male",
    "hospitalId": "H-302",
    "organRequired": "Lungs",
    "registeredAt": "2026-01-30T21:51:21.788521",
    "status": "active",
    "submissionType": "backend-api",
    "test_lungs_ct": "4",
    "test_lungs_ct_date": "2025-12-31",
    "test_lungs_echo": "2",
    "test_lungs_echo_date": "2026-01-16",
    "test_lungs_pftsTest": "1",
    "test_lungs_pftsTest_date": "2026-01-20",
    "test_lungs_xray": "10",
    "test_lungs_xray_date": "2026-01-03",
    "urgencyStatus": "Moderate"
  },
  {
    "abhaId": "24310100387144",
    "bloodGroup": "O-",
    "diagnosis": "Diagnosis_2896d63c",
    "dob": "1982-11-03",
    "fullName": "Recipient_095c53",
    "gender": "Male",
    "hospitalId": "H-870",
    "organRequired": "Lungs",
    "registeredAt": "2026-01-30T21:51:21.788555",
    "status": "active",
    "submissionType": "backend-api",
    "test_lungs_ct": "8",
    "test_lungs_ct_date": "2026-01-12",
    "test_lungs_echo": "3",
    "test_lungs_echo_date": "2026-01-17",
    "test_lungs_pftsTest": "3",
    "test_lungs_pftsTest_date": "2026-01-14",
    "test_lungs_xray": "4",
    "test_lungs_xray_date": "2025-12-31",
    "urgencyStatus": "Moderate"
  },
  {
    "abhaId": "53095920133777",
    "bloodGroup": "O-",
    "diagnosis": "Diagnosis_feb962a4",
    "dob": "1965-07-12",
    "fullName": "Recipient_8c3299",
    "gender": "Male",
    "hospitalId": "H-777",
    "organRequired": "Kidney",
    "registeredAt": "2026-01-30T21:51:21.788590",
    "status": "active",
    "submissionType": "backend-api",
    "test_kidney_ct": "3",
    "test_kidney_ct_date": "2026-01-22",
    "test_kidney_echo": "10",
    "test_kidney_echo_date": "2026-01-07",
    "test_kidney_pftsTest": "7",
    "test_kidney_pftsTest_date": "2026-01-18",
    "test_kidney_xray": "6",
    "test_kidney_xray_date": "2026-01-23",
    "urgencyStatus": "Critical (ICU)"
  },
  {
    "abhaId": "15385795141585",
    "bloodGroup": "B-",
    "diagnosis": "Diagnosis_2b172454",
    "dob": "1991-09-07",
    "fullName": "Recipient_1a5823",
    "gender": "Male",
    "hospitalId": "H-799",
    "organRequired": "Heart",
    "registeredAt": "2026-01-30T21:51:21.788625",
    "status": "active",
    "submissionType": "backend-api",
    "test_heart_ct": "7",
    "test_heart_ct_date": "2026-01-06",
    "test_heart_echo": "9",
    "test_heart_echo_date": "2026-01-05",
    "test_heart_pftsTest": "8",
    "test_heart_pftsTest_date": "2026-01-24",
    "test_heart_xray": "10",
    "test_heart_xray_date": "2026-01-11",
    "urgencyStatus": "Urgent (Hospitalized)"
  },
  {
    "abhaId": "32181266413095",
    "bloodGroup": "AB+",
    "diagnosis": "Diagnosis_28559047",
    "dob": "1998-02-27",
    "fullName": "Recipient_ba67f8",
    "gender": "Male",
    "hospitalId": "H-182",
    "organRequired": "Kidney",
    "registeredAt": "2026-01-30T21:51:21.788659",
    "status": "active",
    "submissionType": "backend-api",
    "test_kidney_ct": "4",
    "test_kidney_ct_date": "2026-01-06",
    "test_kidney_echo": "3",
    "test_kidney_echo_date": "2026-01-09",
    "test_kidney_pftsTest": "2",
    "test_kidney_pftsTest_date": "2026-01-16",
    "test_kidney_xray": "10",
    "test_kidney_xray_date": "2026-01-27",
    "urgencyStatus": "Stable"
  },
  {
    "abhaId": "24885752650613",
    "bloodGroup": "O+",
    "diagnosis": "Diagnosis_7179ebc7",
    "dob": "1999-10-04",
    "fullName": "Recipient_4ad412",
    "gender": "Male",
    "hospitalId": "H-967",
    "organRequired": "Heart",
    "registeredAt": "2026-01-30T21:51:21.788696",
    "status": "active",
    "submissionType": "backend-api",
    "test_heart_ct": "8",
    "test_heart_ct_date": "2026-01-18",
    "test_heart_echo": "1",
    "test_heart_echo_date": "2026-01-03",
    "test_heart_pftsTest": "10",
    "test_heart_pftsTest_date": "2026-01-08",
    "test_heart_xray": "6",
    "test_heart_xray_date": "2026-01-01",
    "urgencyStatus": "Stable"
  },
  {
    "abhaId": "34068435741986",
    "bloodGroup": "O-",
    "diagnosis": "Diagnosis_5343aabe",
    "dob": "1993-09-12",
    "fullName": "Recipient_97fb8b",
    "gender": "Male",
    "hospitalId": "H-907",
    "organRequired": "Liver",
    "registeredAt": "2026-01-30T21:51:21.788729",
    "status": "active",
    "submissionType": "backend-api",
    "test_liver_ct": "6",
    "test_liver_ct_date": "2026-01-19",
    "test_liver_echo": "3",
    "test_liver_echo_date": "2026-01-16",
    "test_liver_pftsTest": "5",
    "test_liver_pftsTest_date": "2026-01-21",
    "test_liver_xray": "6",
    "test_liver_xray_date": "2026-01-20",
    "urgencyStatus": "Stable"
  },
  {
    "abhaId": "78422643965882",
    "bloodGroup": "AB+",
    "diagnosis": "Diagnosis_1c77a1dc",
    "dob": "1996-06-06",
    "fullName": "Recipient_4417ae",
    "gender": "Male",
    "hospitalId": "H-480",
    "organRequired": "Lungs",
    "registeredAt": "2026-01-30T21:51:21.788764",
    "status": "active",
    "submissionType": "backend-api",
    "test_lungs_ct": "5",
    "test_lungs_ct_date": "2026-01-17",
    "test_lungs_echo": "7",
    "test_lungs_echo_date": "2026-01-11",
    "test_lungs_pftsTest": "10",
    "test_lungs_pftsTest_date": "2026-01-16",
    "test_lungs_xray": "2",
    "test_lungs_xray_date": "2026-01-26",
    "urgencyStatus": "Urgent (Hospitalized)"
  },
  {
    "abhaId": "94764587620881",
    "bloodGroup": "B-",
    "diagnosis": "Diagnosis_e5cb827c",
    "dob": "1995-11-14",
    "fullName": "Recipient_8aab74",
    "gender": "Female",
    "hospitalId": "H-991",
    "organRequired": "Kidney",
    "registeredAt": "2026-01-30T21:51:21.788800",
    "status": "active",
    "submissionType": "backend-api",
    "test_kidney_ct": "1",
    "test_kidney_ct_date": "2026-01-27",
    "test_kidney_echo": "6",
    "test_kidney_echo_date": "2026-01-21",
    "test_kidney_pftsTest": "8",
    "test_kidney_pftsTest_date": "2026-01-23",
    "test_kidney_xray": "2",
    "test_kidney_xray_date": "2026-01-09",
    "urgencyStatus": "Urgent (Hospitalized)"
  },
  {
    "abhaId": "40549686982011",
    "bloodGroup": "B-",
    "diagnosis": "Diagnosis_86016ae6",
    "dob": "1997-09-02",
    "fullName": "Recipient_d92447",
    "gender": "Female",
    "hospitalId": "H-765",
    "organRequired": "Lungs",
    "registeredAt": "2026-01-30T21:51:21.788841",
    "status": "active",
    "submissionType": "backend-api",
    "test_lungs_ct": "3",
    "test_lungs_ct_date": "2026-01-14",
    "test_lungs_echo": "9",
    "test_lungs_echo_date": "2026-01-07",
    "test_lungs_pftsTest": "5",
    "test_lungs_pftsTest_date": "2026-01-29",
    "test_lungs_xray": "10",
    "test_lungs_xray_date": "2026-01-01",
    "urgencyStatus": "Moderate"
  },
  {
    "abhaId": "74984899915572",
    "bloodGroup": "A-",
    "diagnosis": "Diagnosis_660b7a26",
    "dob": "2004-11-18",
    "fullName": "Recipient_9859d9",
    "gender": "Female",
    "hospitalId": "H-140",
    "organRequired": "Lungs",
    "registeredAt": "2026-01-30T21:51:21.788876",
    "status": "active",
    "submissionType": "backend-api",
    "test_lungs_ct": "9",
    "test_lungs_ct_date": "2026-01-20",
    "test_lungs_echo": "2",
    "test_lungs_echo_date": "2026-01-23",
    "test_lungs_pftsTest": "2",
    "test_lungs_pftsTest_date": "2026-01-03",
    "test_lungs_xray": "3",
    "test_lungs_xray_date": "2026-01-04",
    "urgencyStatus": "Urgent (Hospitalized)"
  },
  {
    "abhaId": "70062597552868",
    "bloodGroup": "AB+",
    "diagnosis": "Diagnosis_9f9fe315",
    "dob": "1990-05-25",
    "fullName": "Recipient_802587",
    "gender": "Female",
    "hospitalId": "H-220",
    "organRequired": "Lungs",
    "registeredAt": "2026-01-30T21:51:21.788912",
    "status": "active",
    "submissionType": "backend-api",
    "test_lungs_ct": "8",
    "test_lungs_ct_date": "2026-01-23",
    "test_lungs_echo": "2",
    "test_lungs_echo_date": "2026-01-25",
    "test_lungs_pftsTest": "2",
    "test_lungs_pftsTest_date": "2026-01-01",
    "test_lungs_xray": "8",
    "test_lungs_xray_date": "2026-01-18",
    "urgencyStatus": "Stable"
  },
  {
    "abhaId": "22278220188537",
    "bloodGroup": "AB-",
    "diagnosis": "Diagnosis_b233ef35",
    "dob": "1964-08-11",
    "fullName": "Recipient_007720",
    "gender": "Female",
    "hospitalId": "H-656",
    "organRequired": "Liver",
    "registeredAt": "2026-01-30T21:51:21.788946",
    "status": "active",
    "submissionType": "backend-api",
    "test_liver_ct": "10",
    "test_liver_ct_date": "2026-01-02",
    "test_liver_echo": "4",
    "test_liver_echo_date": "2026-01-29",
    "test_liver_pftsTest": "8",
    "test_liver_pftsTest_date": "2026-01-18",
    "test_liver_xray": "8",
    "test_liver_xray_date": "2026-01-27",
    "urgencyStatus": "Moderate"
  },
  {
    "abhaId": "69406021123259",
    "bloodGroup": "A-",
    "diagnosis": "Diagnosis_36181d47",
    "dob": "1994-05-22",
    "fullName": "Recipient_418102",
    "gender": "Male",
    "hospitalId": "H-786",
    "organRequired": "Heart",
    "registeredAt": "2026-01-30T21:51:21.788984",
    "status": "active",
    "submissionType": "backend-api",
    "test_heart_ct": "9",
    "test_heart_ct_date": "2026-01-04",
    "test_heart_echo": "3",
    "test_heart_echo_date": "2026-01-19",
    "test_heart_pftsTest": "3",
    "test_heart_pftsTest_date": "2025-12-31",
    "test_heart_xray": "8",
    "test_heart_xray_date": "2026-01-29",
    "urgencyStatus": "Urgent (Hospitalized)"
  },
  {
    "abhaId": "82553396088705",
    "bloodGroup": "O-",
    "diagnosis": "Diagnosis_d058a904",
    "dob": "1982-06-03",
    "fullName": "Recipient_bf4801",
    "gender": "Female",
    "hospitalId": "H-470",
    "organRequired": "Lungs",
    "registeredAt": "2026-01-30T21:51:21.789019",
    "status": "active",
    "submissionType": "backend-api",
    "test_lungs_ct": "8",
    "test_lungs_ct_date": "2025-12-31",
    "test_lungs_echo": "3",
    "test_lungs_echo_date": "2026-01-27",
    "test_lungs_pftsTest": "3",
    "test_lungs_pftsTest_date": "2026-01-10",
    "test_lungs_xray": "5",
    "test_lungs_xray_date": "2026-01-27",
    "urgencyStatus": "Critical (ICU)"
  },
  {
    "abhaId": "44936094966425",
    "bloodGroup": "A-",
    "diagnosis": "Diagnosis_bde60091",
    "dob": "1967-10-19",
    "fullName": "Recipient_7d0112",
    "gender": "Female",
    "hospitalId": "H-554",
    "organRequired": "Lungs",
    "registeredAt": "2026-01-30T21:51:21.789056",
    "status": "active",
    "submissionType": "backend-api",
    "test_lungs_ct": "4",
    "test_lungs_ct_date": "2026-01-11",
    "test_lungs_echo": "1",
    "test_lungs_echo_date": "2026-01-05",
    "test_lungs_pftsTest": "3",
    "test_lungs_pftsTest_date": "2026-01-12",
    "test_lungs_xray": "5",
    "test_lungs_xray_date": "2026-01-19",
    "urgencyStatus": "Moderate"
  },
  {
    "abhaId": "91164767565043",
    "bloodGroup": "O+",
    "diagnosis": "Diagnosis_75dc0c8a",
    "dob": "2003-10-25",
    "fullName": "Recipient_92af09",
    "gender": "Female",
    "hospitalId": "H-626",
    "organRequired": "Heart",
    "registeredAt": "2026-01-30T21:51:21.789103",
    "status": "active",
    "submissionType": "backend-api",
    "test_heart_ct": "10",
    "test_heart_ct_date": "2026-01-04",
    "test_heart_echo": "10",
    "test_heart_echo_date": "2026-01-28",
    "test_heart_pftsTest": "8",
    "test_heart_pftsTest_date": "2026-01-16",
    "test_heart_xray": "4",
    "test_heart_xray_date": "2026-01-29",
    "urgencyStatus": "Critical (ICU)"
  },
  {
    "abhaId": "64933456464558",
    "bloodGroup": "AB+",
    "diagnosis": "Diagnosis_be033704",
    "dob": "1964-03-03",
    "fullName": "Recipient_540667",
    "gender": "Male",
    "hospitalId": "H-164",
    "organRequired": "Lungs",
    "registeredAt": "2026-01-30T21:51:21.789157",
    "status": "active",
    "submissionType": "backend-api",
    "test_lungs_ct": "3",
    "test_lungs_ct_date": "2026-01-16",
    "test_lungs_echo": "8",
    "test_lungs_echo_date": "2026-01-11",
    "test_lungs_pftsTest": "4",
    "test_lungs_pftsTest_date": "2026-01-24",
    "test_lungs_xray": "10",
    "test_lungs_xray_date": "2026-01-26",
    "urgencyStatus": "Moderate"
  },
  {
    "abhaId": "22886245582930",
    "bloodGroup": "A+",
    "diagnosis": "Diagnosis_0229f120",
    "dob": "1995-07-31",
    "fullName": "Recipient_7caf50",
    "gender": "Female",
    "hospitalId": "H-463",
    "organRequired": "Lungs",
    "registeredAt": "2026-01-30T21:51:21.789209",
    "status": "active",
    "submissionType": "backend-api",
    "test_lungs_ct": "9",
    "test_lungs_ct_date": "2026-01-18",
    "test_lungs_echo": "7",
    "test_lungs_echo_date": "2025-12-31",
    "test_lungs_pftsTest": "6",
    "test_lungs_pftsTest_date": "2026-01-22",
    "test_lungs_xray": "4",
    "test_lungs_xray_date": "2026-01-11",
    "urgencyStatus": "Critical (ICU)"
  },
  {
    "abhaId": "51581543041710",
    "bloodGroup": "AB+",
    "diagnosis": "Diagnosis_cdb32119",
    "dob": "1975-03-30",
    "fullName": "Recipient_683fd2",
    "gender": "Male",
    "hospitalId": "H-974",
    "organRequired": "Liver",
    "registeredAt": "2026-01-30T21:51:21.789258",
    "status": "active",
    "submissionType": "backend-api",
    "test_liver_ct": "10",
    "test_liver_ct_date": "2026-01-14",
    "test_liver_echo": "8",
    "test_liver_echo_date": "2026-01-05",
    "test_liver_pftsTest": "9",
    "test_liver_pftsTest_date": "2026-01-18",
    "test_liver_xray": "7",
    "test_liver_xray_date": "2026-01-11",
    "urgencyStatus": "Urgent (Hospitalized)"
  },
  {
    "abhaId": "82455189708179",
    "bloodGroup": "AB+",
    "diagnosis": "Diagnosis_4f18cca0",
    "dob": "1983-09-12",
    "fullName": "Recipient_415b8b",
    "gender": "Female",
    "hospitalId": "H-707",
    "organRequired": "Heart",
    "registeredAt": "2026-01-30T21:51:21.789305",
    "status": "active",
    "submissionType": "backend-api",
    "test_heart_ct": "10",
    "test_heart_ct_date": "2026-01-13",
    "test_heart_echo": "1",
    "test_heart_echo_date": "2025-12-31",
    "test_heart_pftsTest": "1",
    "test_heart_pftsTest_date": "2026-01-29",
    "test_heart_xray": "2",
    "test_heart_xray_date": "2026-01-22",
    "urgencyStatus": "Stable"
  },
  {
    "abhaId": "41498508474470",
    "bloodGroup": "B+",
    "diagnosis": "Diagnosis_d65e0457",
    "dob": "1991-09-18",
    "fullName": "Recipient_5b0396",
    "gender": "Female",
    "hospitalId": "H-921",
    "organRequired": "Lungs",
    "registeredAt": "2026-01-30T21:51:21.789361",
    "status": "active",
    "submissionType": "backend-api",
    "test_lungs_ct": "3",
    "test_lungs_ct_date": "2026-01-13",
    "test_lungs_echo": "3",
    "test_lungs_echo_date": "2026-01-21",
    "test_lungs_pftsTest": "5",
    "test_lungs_pftsTest_date": "2026-01-09",
    "test_lungs_xray": "2",
    "test_lungs_xray_date": "2026-01-03",
    "urgencyStatus": "Moderate"
  },
  {
    "abhaId": "67524315577939",
    "bloodGroup": "O-",
    "diagnosis": "Diagnosis_0082b074",
    "dob": "1982-05-16",
    "fullName": "Recipient_1e6f78",
    "gender": "Female",
    "hospitalId": "H-678",
    "organRequired": "Liver",
    "registeredAt": "2026-01-30T21:51:21.789406",
    "status": "active",
    "submissionType": "backend-api",
    "test_liver_ct": "4",
    "test_liver_ct_date": "2026-01-15",
    "test_liver_echo": "1",
    "test_liver_echo_date": "2026-01-13",
    "test_liver_pftsTest": "6",
    "test_liver_pftsTest_date": "2026-01-09",
    "test_liver_xray": "2",
    "test_liver_xray_date": "2026-01-06",
    "urgencyStatus": "Urgent (Hospitalized)"
  },
  {
    "abhaId": "47607966010733",
    "bloodGroup": "B+",
    "diagnosis": "Diagnosis_74f878f6",
    "dob": "1985-08-24",
    "fullName": "Recipient_6812cc",
    "gender": "Male",
    "hospitalId": "H-146",
    "organRequired": "Liver",
    "registeredAt": "2026-01-30T21:51:21.789454",
    "status": "active",
    "submissionType": "backend-api",
    "test_liver_ct": "4",
    "test_liver_ct_date": "2026-01-16",
    "test_liver_echo": "5",
    "test_liver_echo_date": "2025-12-31",
    "test_liver_pftsTest": "4",
    "test_liver_pftsTest_date": "2026-01-13",
    "test_liver_xray": "7",
    "test_liver_xray_date": "2026-01-07",
    "urgencyStatus": "Moderate"
  },
  {
    "abhaId": "14112373721621",
    "bloodGroup": "O-",
    "diagnosis": "Diagnosis_9eb34413",
    "dob": "1994-02-01",
    "fullName": "Recipient_cfd28f",
    "gender": "Female",
    "hospitalId": "H-416",
    "organRequired": "Lungs",
    "registeredAt": "2026-01-30T21:51:21.789501",
    "status": "active",
    "submissionType": "backend-api",
    "test_lungs_ct": "10",
    "test_lungs_ct_date": "2026-01-18",
    "test_lungs_echo": "3",
    "test_lungs_echo_date": "2026-01-12",
    "test_lungs_pftsTest": "9",
    "test_lungs_pftsTest_date": "2026-01-16",
    "test_lungs_xray": "5",
    "test_lungs_xray_date": "2026-01-29",
    "urgencyStatus": "Critical (ICU)"
  },
  {
    "abhaId": "11688409627996",
    "bloodGroup": "A-",
    "diagnosis": "Diagnosis_019c7ead",
    "dob": "1988-01-15",
    "fullName": "Recipient_db3e21",
    "gender": "Female",
    "hospitalId": "H-434",
    "organRequired": "Heart",
    "registeredAt": "2026-01-30T21:51:21.789548",
    "status": "active",
    "submissionType": "backend-api",
    "test_heart_ct": "3",
    "test_heart_ct_date": "2026-01-07",
    "test_heart_echo": "9",
    "test_heart_echo_date": "2026-01-14",
    "test_heart_pftsTest": "5",
    "test_heart_pftsTest_date": "2026-01-17",
    "test_heart_xray": "2",
    "test_heart_xray_date": "2025-12-31",
    "urgencyStatus": "Urgent (Hospitalized)"
  },
  {
    "abhaId": "53528917557513",
    "bloodGroup": "A-",
    "diagnosis": "Diagnosis_5a0a9089",
    "dob": "1996-10-09",
    "fullName": "Recipient_07ee08",
    "gender": "Male",
    "hospitalId": "H-999",
    "organRequired": "Liver",
    "registeredAt": "2026-01-30T21:51:21.789588",
    "status": "active",
    "submissionType": "backend-api",
    "test_liver_ct": "3",
    "test_liver_ct_date": "2026-01-01",
    "test_liver_echo": "10",
    "test_liver_echo_date": "2026-01-06",
    "test_liver_pftsTest": "2",
    "test_liver_pftsTest_date": "2026-01-23",
    "test_liver_xray": "6",
    "test_liver_xray_date": "2026-01-18",
    "urgencyStatus": "Stable"
  },
  {
    "abhaId": "47744400984715",
    "bloodGroup": "A+",
    "diagnosis": "Diagnosis_406a0c4d",
    "dob": "1988-08-27",
    "fullName": "Recipient_ec923d",
    "gender": "Male",
    "hospitalId": "H-371",
    "organRequired": "Kidney",
    "registeredAt": "2026-01-30T21:51:21.789616",
    "status": "active",
    "submissionType": "backend-api",
    "test_kidney_ct": "2",
    "test_kidney_ct_date": "2026-01-04",
    "test_kidney_echo": "2",
    "test_kidney_echo_date": "2026-01-15",
    "test_kidney_pftsTest": "7",
    "test_kidney_pftsTest_date": "2026-01-15",
    "test_kidney_xray": "1",
    "test_kidney_xray_date": "2026-01-14",
    "urgencyStatus": "Moderate"
  },
  {
    "abhaId": "73867573271769",
    "bloodGroup": "B-",
    "diagnosis": "Diagnosis_05cbfc84",
    "dob": "1970-11-03",
    "fullName": "Recipient_39b0b4",
    "gender": "Female",
    "hospitalId": "H-328",
    "organRequired": "Kidney",
    "registeredAt": "2026-01-30T21:51:21.789644",
    "status": "active",
    "submissionType": "backend-api",
    "test_kidney_ct": "2",
    "test_kidney_ct_date": "2026-01-14",
    "test_kidney_echo": "3",
    "test_kidney_echo_date": "2026-01-18",
    "test_kidney_pftsTest": "8",
    "test_kidney_pftsTest_date": "2025-12-31",
    "test_kidney_xray": "8",
    "test_kidney_xray_date": "2026-01-10",
    "urgencyStatus": "Stable"
  },
  {
    "abhaId": "23862528858468",
    "bloodGroup": "O+",
    "diagnosis": "Diagnosis_7eb5623e",
    "dob": "1988-06-26",
    "fullName": "Recipient_5d16f4",
    "gender": "Male",
    "hospitalId": "H-442",
    "organRequired": "Kidney",
    "registeredAt": "2026-01-30T21:51:21.789672",
    "status": "active",
    "submissionType": "backend-api",
    "test_kidney_ct": "9",
    "test_kidney_ct_date": "2025-12-31",
    "test_kidney_echo": "2",
    "test_kidney_echo_date": "2026-01-19",
    "test_kidney_pftsTest": "8",
    "test_kidney_pftsTest_date": "2026-01-23",
    "test_kidney_xray": "3",
    "test_kidney_xray_date": "2026-01-14",
    "urgencyStatus": "Stable"
  },
  {
    "abhaId": "51479428077825",
    "bloodGroup": "AB-",
    "diagnosis": "Diagnosis_26a0ebd0",
    "dob": "1982-03-04",
    "fullName": "Recipient_44bd56",
    "gender": "Male",
    "hospitalId": "H-825",
    "organRequired": "Heart",
    "registeredAt": "2026-01-30T21:51:21.789700",
    "status": "active",
    "submissionType": "backend-api",
    "test_heart_ct": "7",
    "test_heart_ct_date": "2026-01-28",
    "test_heart_echo": "2",
    "test_heart_echo_date": "2026-01-18",
    "test_heart_pftsTest": "6",
    "test_heart_pftsTest_date": "2026-01-05",
    "test_heart_xray": "6",
    "test_heart_xray_date": "2026-01-01",
    "urgencyStatus": "Urgent (Hospitalized)"
  },
  {
    "abhaId": "47561144008288",
    "bloodGroup": "A-",
    "diagnosis": "Diagnosis_ee978fcc",
    "dob": "1975-05-12",
    "fullName": "Recipient_aa9a8d",
    "gender": "Male",
    "hospitalId": "H-739",
    "organRequired": "Lungs",
    "registeredAt": "2026-01-30T21:51:21.789729",
    "status": "active",
    "submissionType": "backend-api",
    "test_lungs_ct": "2",
    "test_lungs_ct_date": "2025-12-31",
    "test_lungs_echo": "4",
    "test_lungs_echo_date": "2026-01-06",
    "test_lungs_pftsTest": "7",
    "test_lungs_pftsTest_date": "2026-01-07",
    "test_lungs_xray": "8",
    "test_lungs_xray_date": "2025-12-31",
    "urgencyStatus": "Urgent (Hospitalized)"
  },
  {
    "abhaId": "94494594091000",
    "bloodGroup": "B+",
    "diagnosis": "Diagnosis_93d66cf0",
    "dob": "1966-05-28",
    "fullName": "Recipient_9257a7",
    "gender": "Male",
    "hospitalId": "H-387",
    "organRequired": "Kidney",
    "registeredAt": "2026-01-30T21:51:21.789759",
    "status": "active",
    "submissionType": "backend-api",
    "test_kidney_ct": "2",
    "test_kidney_ct_date": "2026-01-10",
    "test_kidney_echo": "10",
    "test_kidney_echo_date": "2026-01-04",
    "test_kidney_pftsTest": "7",
    "test_kidney_pftsTest_date": "2026-01-03",
    "test_kidney_xray": "7",
    "test_kidney_xray_date": "2026-01-29",
    "urgencyStatus": "Critical (ICU)"
  },
  {
    "abhaId": "78512310013469",
    "bloodGroup": "AB+",
    "diagnosis": "Diagnosis_42d84478",
    "dob": "1992-07-08",
    "fullName": "Recipient_b0b08a",
    "gender": "Male",
    "hospitalId": "H-937",
    "organRequired": "Lungs",
    "registeredAt": "2026-01-30T21:51:21.789799",
    "status": "active",
    "submissionType": "backend-api",
    "test_lungs_ct": "2",
    "test_lungs_ct_date": "2025-12-31",
    "test_lungs_echo": "10",
    "test_lungs_echo_date": "2026-01-10",
    "test_lungs_pftsTest": "6",
    "test_lungs_pftsTest_date": "2026-01-09",
    "test_lungs_xray": "7",
    "test_lungs_xray_date": "2026-01-22",
    "urgencyStatus": "Critical (ICU)"
  },
  {
    "abhaId": "14934957272269",
    "bloodGroup": "A+",
    "diagnosis": "Diagnosis_9dbd9208",
    "dob": "1977-04-10",
    "fullName": "Recipient_e39396",
    "gender": "Female",
    "hospitalId": "H-971",
    "organRequired": "Heart",
    "registeredAt": "2026-01-30T21:51:21.789827",
    "status": "active",
    "submissionType": "backend-api",
    "test_heart_ct": "10",
    "test_heart_ct_date": "2026-01-22",
    "test_heart_echo": "9",
    "test_heart_echo_date": "2026-01-05",
    "test_heart_pftsTest": "2",
    "test_heart_pftsTest_date": "2026-01-10",
    "test_heart_xray": "5",
    "test_heart_xray_date": "2026-01-13",
    "urgencyStatus": "Stable"
  },
  {
    "abhaId": "54719223587742",
    "bloodGroup": "O+",
    "diagnosis": "Diagnosis_80d64367",
    "dob": "1960-05-14",
    "fullName": "Recipient_2095ae",
    "gender": "Male",
    "hospitalId": "H-604",
    "organRequired": "Lungs",
    "registeredAt": "2026-01-30T21:51:21.789855",
    "status": "active",
    "submissionType": "backend-api",
    "test_lungs_ct": "8",
    "test_lungs_ct_date": "2026-01-17",
    "test_lungs_echo": "10",
    "test_lungs_echo_date": "2026-01-27",
    "test_lungs_pftsTest": "2",
    "test_lungs_pftsTest_date": "2026-01-26",
    "test_lungs_xray": "5",
    "test_lungs_xray_date": "2026-01-13",
    "urgencyStatus": "Stable"
  },
  {
    "abhaId": "62690363205925",
    "bloodGroup": "A-",
    "diagnosis": "Diagnosis_46d4b846",
    "dob": "1990-06-18",
    "fullName": "Recipient_40bacf",
    "gender": "Female",
    "hospitalId": "H-933",
    "organRequired": "Liver",
    "registeredAt": "2026-01-30T21:51:21.789883",
    "status": "active",
    "submissionType": "backend-api",
    "test_liver_ct": "5",
    "test_liver_ct_date": "2026-01-08",
    "test_liver_echo": "6",
    "test_liver_echo_date": "2026-01-09",
    "test_liver_pftsTest": "7",
    "test_liver_pftsTest_date": "2026-01-13",
    "test_liver_xray": "2",
    "test_liver_xray_date": "2026-01-11",
    "urgencyStatus": "Stable"
  },
  {
    "abhaId": "38848321970033",
    "bloodGroup": "AB-",
    "diagnosis": "Diagnosis_2ed8872d",
    "dob": "2000-01-12",
    "fullName": "Recipient_1876da",
    "gender": "Male",
    "hospitalId": "H-104",
    "organRequired": "Lungs",
    "registeredAt": "2026-01-30T21:51:21.789913",
    "status": "active",
    "submissionType": "backend-api",
    "test_lungs_ct": "3",
    "test_lungs_ct_date": "2026-01-15",
    "test_lungs_echo": "1",
    "test_lungs_echo_date": "2026-01-11",
    "test_lungs_pftsTest": "9",
    "test_lungs_pftsTest_date": "2026-01-24",
    "test_lungs_xray": "3",
    "test_lungs_xray_date": "2026-01-24",
    "urgencyStatus": "Moderate"
  },
  {
    "abhaId": "29093814140084",
    "bloodGroup": "O+",
    "diagnosis": "Diagnosis_af427774",
    "dob": "1975-11-07",
    "fullName": "Recipient_1ed44c",
    "gender": "Male",
    "hospitalId": "H-974",
    "organRequired": "Lungs",
    "registeredAt": "2026-01-30T21:51:21.789940",
    "status": "active",
    "submissionType": "backend-api",
    "test_lungs_ct": "10",
    "test_lungs_ct_date": "2026-01-28",
    "test_lungs_echo": "7",
    "test_lungs_echo_date": "2026-01-05",
    "test_lungs_pftsTest": "8",
    "test_lungs_pftsTest_date": "2025-12-31",
    "test_lungs_xray": "4",
    "test_lungs_xray_date": "2026-01-18",
    "urgencyStatus": "Critical (ICU)"
  },
  {
    "abhaId": "18590983662008",
    "bloodGroup": "B+",
    "diagnosis": "Diagnosis_db6ec261",
    "dob": "2009-07-28",
    "fullName": "Recipient_580b49",
    "gender": "Male",
    "hospitalId": "H-791",
    "organRequired": "Heart",
    "registeredAt": "2026-01-30T21:51:21.789968",
    "status": "active",
    "submissionType": "backend-api",
    "test_heart_ct": "1",
    "test_heart_ct_date": "2025-12-31",
    "test_heart_echo": "2",
    "test_heart_echo_date": "2026-01-10",
    "test_heart_pftsTest": "9",
    "test_heart_pftsTest_date": "2026-01-03",
    "test_heart_xray": "10",
    "test_heart_xray_date": "2026-01-23",
    "urgencyStatus": "Urgent (Hospitalized)"
  },
  {
    "abhaId": "65397673446205",
    "bloodGroup": "O-",
    "diagnosis": "Diagnosis_3a39d455",
    "dob": "1966-01-06",
    "fullName": "Recipient_e7f53f",
    "gender": "Male",
    "hospitalId": "H-297",
    "organRequired": "Lungs",
    "registeredAt": "2026-01-30T21:51:21.789998",
    "status": "active",
    "submissionType": "backend-api",
    "test_lungs_ct": "2",
    "test_lungs_ct_date": "2026-01-02",
    "test_lungs_echo": "3",
    "test_lungs_echo_date": "2026-01-02",
    "test_lungs_pftsTest": "9",
    "test_lungs_pftsTest_date": "2026-01-13",
    "test_lungs_xray": "8",
    "test_lungs_xray_date": "2026-01-12",
    "urgencyStatus": "Stable"
  },
  {
    "abhaId": "44404136071472",
    "bloodGroup": "B-",
    "diagnosis": "Diagnosis_73ba21c3",
    "dob": "1974-01-28",
    "fullName": "Recipient_59113d",
    "gender": "Female",
    "hospitalId": "H-765",
    "organRequired": "Kidney",
    "registeredAt": "2026-01-30T21:51:21.790025",
    "status": "active",
    "submissionType": "backend-api",
    "test_kidney_ct": "10",
    "test_kidney_ct_date": "2026-01-03",
    "test_kidney_echo": "8",
    "test_kidney_echo_date": "2026-01-28",
    "test_kidney_pftsTest": "4",
    "test_kidney_pftsTest_date": "2026-01-16",
    "test_kidney_xray": "4",
    "test_kidney_xray_date": "2026-01-08",
    "urgencyStatus": "Urgent (Hospitalized)"
  },
  {
    "abhaId": "16351287112259",
    "bloodGroup": "AB-",
    "diagnosis": "Diagnosis_9386eae1",
    "dob": "1964-08-30",
    "fullName": "Recipient_29b06d",
    "gender": "Female",
    "hospitalId": "H-497",
    "organRequired": "Lungs",
    "registeredAt": "2026-01-30T21:51:21.790052",
    "status": "active",
    "submissionType": "backend-api",
    "test_lungs_ct": "2",
    "test_lungs_ct_date": "2026-01-23",
    "test_lungs_echo": "4",
    "test_lungs_echo_date": "2026-01-17",
    "test_lungs_pftsTest": "3",
    "test_lungs_pftsTest_date": "2026-01-16",
    "test_lungs_xray": "1",
    "test_lungs_xray_date": "2026-01-02",
    "urgencyStatus": "Moderate"
  },
  {
    "abhaId": "42035038606217",
    "bloodGroup": "AB+",
    "diagnosis": "Diagnosis_aa2dff22",
    "dob": "1997-07-22",
    "fullName": "Recipient_034114",
    "gender": "Male",
    "hospitalId": "H-829",
    "organRequired": "Lungs",
    "registeredAt": "2026-01-30T21:51:21.790081",
    "status": "active",
    "submissionType": "backend-api",
    "test_lungs_ct": "5",
    "test_lungs_ct_date": "2026-01-06",
    "test_lungs_echo": "8",
    "test_lungs_echo_date": "2026-01-23",
    "test_lungs_pftsTest": "3",
    "test_lungs_pftsTest_date": "2026-01-18",
    "test_lungs_xray": "1",
    "test_lungs_xray_date": "2026-01-18",
    "urgencyStatus": "Critical (ICU)"
  },
  {
    "abhaId": "75898593192392",
    "bloodGroup": "A-",
    "diagnosis": "Diagnosis_036ce47d",
    "dob": "1986-10-03",
    "fullName": "Recipient_44352e",
    "gender": "Male",
    "hospitalId": "H-819",
    "organRequired": "Kidney",
    "registeredAt": "2026-01-30T21:51:21.790108",
    "status": "active",
    "submissionType": "backend-api",
    "test_kidney_ct": "2",
    "test_kidney_ct_date": "2026-01-22",
    "test_kidney_echo": "9",
    "test_kidney_echo_date": "2026-01-04",
    "test_kidney_pftsTest": "9",
    "test_kidney_pftsTest_date": "2026-01-27",
    "test_kidney_xray": "8",
    "test_kidney_xray_date": "2026-01-02",
    "urgencyStatus": "Moderate"
  },
  {
    "abhaId": "55422132111496",
    "bloodGroup": "O+",
    "diagnosis": "Diagnosis_60eeb1f3",
    "dob": "2007-10-22",
    "fullName": "Recipient_207028",
    "gender": "Female",
    "hospitalId": "H-427",
    "organRequired": "Kidney",
    "registeredAt": "2026-01-30T21:51:21.790135",
    "status": "active",
    "submissionType": "backend-api",
    "test_kidney_ct": "4",
    "test_kidney_ct_date": "2026-01-05",
    "test_kidney_echo": "1",
    "test_kidney_echo_date": "2026-01-01",
    "test_kidney_pftsTest": "9",
    "test_kidney_pftsTest_date": "2026-01-01",
    "test_kidney_xray": "10",
    "test_kidney_xray_date": "2026-01-15",
    "urgencyStatus": "Moderate"
  },
  {
    "abhaId": "53118457335622",
    "bloodGroup": "B+",
    "diagnosis": "Diagnosis_1ea993f1",
    "dob": "1998-09-22",
    "fullName": "Recipient_c595a9",
    "gender": "Male",
    "hospitalId": "H-336",
    "organRequired": "Kidney",
    "registeredAt": "2026-01-30T21:51:21.790161",
    "status": "active",
    "submissionType": "backend-api",
    "test_kidney_ct": "1",
    "test_kidney_ct_date": "2026-01-03",
    "test_kidney_echo": "8",
    "test_kidney_echo_date": "2026-01-19",
    "test_kidney_pftsTest": "10",
    "test_kidney_pftsTest_date": "2026-01-08",
    "test_kidney_xray": "4",
    "test_kidney_xray_date": "2026-01-24",
    "urgencyStatus": "Urgent (Hospitalized)"
  },
  {
    "abhaId": "29493267957468",
    "bloodGroup": "A-",
    "diagnosis": "Diagnosis_6fccfc1f",
    "dob": "1990-01-15",
    "fullName": "Recipient_720c41",
    "gender": "Female",
    "hospitalId": "H-192",
    "organRequired": "Lungs",
    "registeredAt": "2026-01-30T21:51:21.790190",
    "status": "active",
    "submissionType": "backend-api",
    "test_lungs_ct": "10",
    "test_lungs_ct_date": "2026-01-16",
    "test_lungs_echo": "8",
    "test_lungs_echo_date": "2026-01-26",
    "test_lungs_pftsTest": "2",
    "test_lungs_pftsTest_date": "2026-01-29",
    "test_lungs_xray": "9",
    "test_lungs_xray_date": "2026-01-13",
    "urgencyStatus": "Stable"
  },
  {
    "abhaId": "32354392761177",
    "bloodGroup": "B-",
    "diagnosis": "Diagnosis_9f8eaba5",
    "dob": "1982-05-01",
    "fullName": "Recipient_9c8c2a",
    "gender": "Male",
    "hospitalId": "H-311",
    "organRequired": "Heart",
    "registeredAt": "2026-01-30T21:51:21.790217",
    "status": "active",
    "submissionType": "backend-api",
    "test_heart_ct": "9",
    "test_heart_ct_date": "2026-01-11",
    "test_heart_echo": "6",
    "test_heart_echo_date": "2026-01-10",
    "test_heart_pftsTest": "8",
    "test_heart_pftsTest_date": "2026-01-14",
    "test_heart_xray": "2",
    "test_heart_xray_date": "2026-01-06",
    "urgencyStatus": "Critical (ICU)"
  },
  {
    "abhaId": "48062894726638",
    "bloodGroup": "O-",
    "diagnosis": "Diagnosis_fc5861ef",
    "dob": "1977-04-25",
    "fullName": "Recipient_db2d04",
    "gender": "Female",
    "hospitalId": "H-173",
    "organRequired": "Heart",
    "registeredAt": "2026-01-30T21:51:21.790248",
    "status": "active",
    "submissionType": "backend-api",
    "test_heart_ct": "5",
    "test_heart_ct_date": "2026-01-13",
    "test_heart_echo": "9",
    "test_heart_echo_date": "2025-12-31",
    "test_heart_pftsTest": "2",
    "test_heart_pftsTest_date": "2026-01-29",
    "test_heart_xray": "8",
    "test_heart_xray_date": "2026-01-26",
    "urgencyStatus": "Critical (ICU)"
  },
  {
    "abhaId": "17197253282569",
    "bloodGroup": "AB+",
    "diagnosis": "Diagnosis_27ab52c9",
    "dob": "1994-05-03",
    "fullName": "Recipient_ae482f",
    "gender": "Male",
    "hospitalId": "H-714",
    "organRequired": "Heart",
    "registeredAt": "2026-01-30T21:51:21.790275",
    "status": "active",
    "submissionType": "backend-api",
    "test_heart_ct": "1",
    "test_heart_ct_date": "2026-01-08",
    "test_heart_echo": "5",
    "test_heart_echo_date": "2026-01-23",
    "test_heart_pftsTest": "7",
    "test_heart_pftsTest_date": "2026-01-01",
    "test_heart_xray": "4",
    "test_heart_xray_date": "2026-01-09",
    "urgencyStatus": "Moderate"
  },
  {
    "abhaId": "76934691504944",
    "bloodGroup": "A+",
    "diagnosis": "Diagnosis_0061e293",
    "dob": "1987-04-30",
    "fullName": "Recipient_0a35d0",
    "gender": "Male",
    "hospitalId": "H-521",
    "organRequired": "Lungs",
    "registeredAt": "2026-01-30T21:51:21.790303",
    "status": "active",
    "submissionType": "backend-api",
    "test_lungs_ct": "3",
    "test_lungs_ct_date": "2026-01-22",
    "test_lungs_echo": "8",
    "test_lungs_echo_date": "2026-01-16",
    "test_lungs_pftsTest": "3",
    "test_lungs_pftsTest_date": "2026-01-02",
    "test_lungs_xray": "4",
    "test_lungs_xray_date": "2026-01-09",
    "urgencyStatus": "Moderate"
  },
  {
    "abhaId": "58392678233794",
    "bloodGroup": "O-",
    "diagnosis": "Diagnosis_5beea813",
    "dob": "1994-10-16",
    "fullName": "Recipient_dfcb44",
    "gender": "Female",
    "hospitalId": "H-130",
    "organRequired": "Heart",
    "registeredAt": "2026-01-30T21:51:21.790331",
    "status": "active",
    "submissionType": "backend-api",
    "test_heart_ct": "8",
    "test_heart_ct_date": "2026-01-09",
    "test_heart_echo": "4",
    "test_heart_echo_date": "2026-01-04",
    "test_heart_pftsTest": "8",
    "test_heart_pftsTest_date": "2026-01-26",
    "test_heart_xray": "6",
    "test_heart_xray_date": "2026-01-15",
    "urgencyStatus": "Urgent (Hospitalized)"
  },
  {
    "abhaId": "65861385647352",
    "bloodGroup": "O-",
    "diagnosis": "Diagnosis_d41085f6",
    "dob": "1964-02-04",
    "fullName": "Recipient_22369a",
    "gender": "Female",
    "hospitalId": "H-480",
    "organRequired": "Heart",
    "registeredAt": "2026-01-30T21:51:21.790357",
    "status": "active",
    "submissionType": "backend-api",
    "test_heart_ct": "8",
    "test_heart_ct_date": "2026-01-25",
    "test_heart_echo": "1",
    "test_heart_echo_date": "2026-01-26",
    "test_heart_pftsTest": "9",
    "test_heart_pftsTest_date": "2026-01-27",
    "test_heart_xray": "9",
    "test_heart_xray_date": "2026-01-23",
    "urgencyStatus": "Stable"
  },
  {
    "abhaId": "44355044205765",
    "bloodGroup": "A+",
    "diagnosis": "Diagnosis_37037401",
    "dob": "1985-12-31",
    "fullName": "Recipient_1a2bac",
    "gender": "Male",
    "hospitalId": "H-738",
    "organRequired": "Liver",
    "registeredAt": "2026-01-30T21:51:21.790386",
    "status": "active",
    "submissionType": "backend-api",
    "test_liver_ct": "4",
    "test_liver_ct_date": "2026-01-27",
    "test_liver_echo": "4",
    "test_liver_echo_date": "2026-01-14",
    "test_liver_pftsTest": "3",
    "test_liver_pftsTest_date": "2026-01-07",
    "test_liver_xray": "3",
    "test_liver_xray_date": "2026-01-18",
    "urgencyStatus": "Critical (ICU)"
  },
  {
    "abhaId": "93772078197479",
    "bloodGroup": "AB-",
    "diagnosis": "Diagnosis_082edecb",
    "dob": "1991-06-01",
    "fullName": "Recipient_4c2e1b",
    "gender": "Female",
    "hospitalId": "H-201",
    "organRequired": "Liver",
    "registeredAt": "2026-01-30T21:51:21.790413",
    "status": "active",
    "submissionType": "backend-api",
    "test_liver_ct": "4",
    "test_liver_ct_date": "2026-01-08",
    "test_liver_echo": "9",
    "test_liver_echo_date": "2026-01-02",
    "test_liver_pftsTest": "9",
    "test_liver_pftsTest_date": "2026-01-16",
    "test_liver_xray": "8",
    "test_liver_xray_date": "2026-01-23",
    "urgencyStatus": "Stable"
  },
  {
    "abhaId": "31921800399438",
    "bloodGroup": "B-",
    "diagnosis": "Diagnosis_4b524743",
    "dob": "1992-03-10",
    "fullName": "Recipient_d4693e",
    "gender": "Male",
    "hospitalId": "H-475",
    "organRequired": "Liver",
    "registeredAt": "2026-01-30T21:51:21.790439",
    "status": "active",
    "submissionType": "backend-api",
    "test_liver_ct": "7",
    "test_liver_ct_date": "2026-01-02",
    "test_liver_echo": "5",
    "test_liver_echo_date": "2026-01-20",
    "test_liver_pftsTest": "4",
    "test_liver_pftsTest_date": "2026-01-15",
    "test_liver_xray": "2",
    "test_liver_xray_date": "2026-01-20",
    "urgencyStatus": "Critical (ICU)"
  },
  {
    "abhaId": "13689685605947",
    "bloodGroup": "A+",
    "diagnosis": "Diagnosis_467b97bb",
    "dob": "1974-01-08",
    "fullName": "Recipient_58eecc",
    "gender": "Male",
    "hospitalId": "H-269",
    "organRequired": "Heart",
    "registeredAt": "2026-01-30T21:51:21.790467",
    "status": "active",
    "submissionType": "backend-api",
    "test_heart_ct": "1",
    "test_heart_ct_date": "2026-01-10",
    "test_heart_echo": "10",
    "test_heart_echo_date": "2026-01-24",
    "test_heart_pftsTest": "2",
    "test_heart_pftsTest_date": "2025-12-31",
    "test_heart_xray": "1",
    "test_heart_xray_date": "2026-01-29",
    "urgencyStatus": "Moderate"
  },
  {
    "abhaId": "22954936922558",
    "bloodGroup": "AB-",
    "diagnosis": "Diagnosis_9f811475",
    "dob": "1994-06-15",
    "fullName": "Recipient_c347c1",
    "gender": "Male",
    "hospitalId": "H-893",
    "organRequired": "Heart",
    "registeredAt": "2026-01-30T21:51:21.790495",
    "status": "active",
    "submissionType": "backend-api",
    "test_heart_ct": "9",
    "test_heart_ct_date": "2026-01-24",
    "test_heart_echo": "1",
    "test_heart_echo_date": "2026-01-06",
    "test_heart_pftsTest": "2",
    "test_heart_pftsTest_date": "2026-01-03",
    "test_heart_xray": "10",
    "test_heart_xray_date": "2026-01-12",
    "urgencyStatus": "Urgent (Hospitalized)"
  },
  {
    "abhaId": "49618985458037",
    "bloodGroup": "AB-",
    "diagnosis": "Diagnosis_0e8c721b",
    "dob": "1964-02-15",
    "fullName": "Recipient_ed66d3",
    "gender": "Male",
    "hospitalId": "H-356",
    "organRequired": "Heart",
    "registeredAt": "2026-01-30T21:51:21.790523",
    "status": "active",
    "submissionType": "backend-api",
    "test_heart_ct": "2",
    "test_heart_ct_date": "2026-01-13",
    "test_heart_echo": "1",
    "test_heart_echo_date": "2025-12-31",
    "test_heart_pftsTest": "7",
    "test_heart_pftsTest_date": "2026-01-16",
    "test_heart_xray": "10",
    "test_heart_xray_date": "2026-01-05",
    "urgencyStatus": "Moderate"
  },
  {
    "abhaId": "27090241105272",
    "bloodGroup": "O-",
    "diagnosis": "Diagnosis_2b28bb9f",
    "dob": "1973-02-11",
    "fullName": "Recipient_d23567",
    "gender": "Male",
    "hospitalId": "H-442",
    "organRequired": "Heart",
    "registeredAt": "2026-01-30T21:51:21.790555",
    "status": "active",
    "submissionType": "backend-api",
    "test_heart_ct": "3",
    "test_heart_ct_date": "2026-01-20",
    "test_heart_echo": "2",
    "test_heart_echo_date": "2026-01-23",
    "test_heart_pftsTest": "9",
    "test_heart_pftsTest_date": "2026-01-22",
    "test_heart_xray": "7",
    "test_heart_xray_date": "2026-01-13",
    "urgencyStatus": "Stable"
  },
  {
    "abhaId": "11986323933597",
    "bloodGroup": "A+",
    "diagnosis": "Diagnosis_cb92e30b",
    "dob": "1985-12-04",
    "fullName": "Recipient_dad32b",
    "gender": "Male",
    "hospitalId": "H-333",
    "organRequired": "Lungs",
    "registeredAt": "2026-01-30T21:51:21.790582",
    "status": "active",
    "submissionType": "backend-api",
    "test_lungs_ct": "8",
    "test_lungs_ct_date": "2026-01-14",
    "test_lungs_echo": "3",
    "test_lungs_echo_date": "2026-01-11",
    "test_lungs_pftsTest": "5",
    "test_lungs_pftsTest_date": "2026-01-14",
    "test_lungs_xray": "1",
    "test_lungs_xray_date": "2026-01-15",
    "urgencyStatus": "Critical (ICU)"
  },
  {
    "abhaId": "48102786066357",
    "bloodGroup": "O-",
    "diagnosis": "Diagnosis_599cea7b",
    "dob": "1972-02-19",
    "fullName": "Recipient_1676c2",
    "gender": "Female",
    "hospitalId": "H-869",
    "organRequired": "Heart",
    "registeredAt": "2026-01-30T21:51:21.790611",
    "status": "active",
    "submissionType": "backend-api",
    "test_heart_ct": "1",
    "test_heart_ct_date": "2026-01-18",
    "test_heart_echo": "1",
    "test_heart_echo_date": "2026-01-17",
    "test_heart_pftsTest": "8",
    "test_heart_pftsTest_date": "2026-01-08",
    "test_heart_xray": "7",
    "test_heart_xray_date": "2026-01-05",
    "urgencyStatus": "Moderate"
  },
  {
    "abhaId": "76770856237470",
    "bloodGroup": "B+",
    "diagnosis": "Diagnosis_da895642",
    "dob": "2006-05-02",
    "fullName": "Recipient_55bfd0",
    "gender": "Male",
    "hospitalId": "H-742",
    "organRequired": "Kidney",
    "registeredAt": "2026-01-30T21:51:21.790638",
    "status": "active",
    "submissionType": "backend-api",
    "test_kidney_ct": "7",
    "test_kidney_ct_date": "2026-01-04",
    "test_kidney_echo": "6",
    "test_kidney_echo_date": "2026-01-07",
    "test_kidney_pftsTest": "8",
    "test_kidney_pftsTest_date": "2026-01-07",
    "test_kidney_xray": "7",
    "test_kidney_xray_date": "2026-01-06",
    "urgencyStatus": "Critical (ICU)"
  },
  {
    "abhaId": "51237335060922",
    "bloodGroup": "AB-",
    "diagnosis": "Diagnosis_d53c4e07",
    "dob": "2009-02-01",
    "fullName": "Recipient_80f80d",
    "gender": "Female",
    "hospitalId": "H-744",
    "organRequired": "Kidney",
    "registeredAt": "2026-01-30T21:51:21.790665",
    "status": "active",
    "submissionType": "backend-api",
    "test_kidney_ct": "10",
    "test_kidney_ct_date": "2026-01-07",
    "test_kidney_echo": "8",
    "test_kidney_echo_date": "2026-01-15",
    "test_kidney_pftsTest": "3",
    "test_kidney_pftsTest_date": "2026-01-25",
    "test_kidney_xray": "2",
    "test_kidney_xray_date": "2026-01-24",
    "urgencyStatus": "Urgent (Hospitalized)"
  },
  {
    "abhaId": "70992980831981",
    "bloodGroup": "AB-",
    "diagnosis": "Diagnosis_7ee1ecdd",
    "dob": "1968-05-27",
    "fullName": "Recipient_c5c92d",
    "gender": "Female",
    "hospitalId": "H-729",
    "organRequired": "Liver",
    "registeredAt": "2026-01-30T21:51:21.790697",
    "status": "active",
    "submissionType": "backend-api",
    "test_liver_ct": "3",
    "test_liver_ct_date": "2026-01-02",
    "test_liver_echo": "3",
    "test_liver_echo_date": "2026-01-23",
    "test_liver_pftsTest": "5",
    "test_liver_pftsTest_date": "2026-01-09",
    "test_liver_xray": "7",
    "test_liver_xray_date": "2026-01-14",
    "urgencyStatus": "Urgent (Hospitalized)"
  },
  {
    "abhaId": "52998895870343",
    "bloodGroup": "AB-",
    "diagnosis": "Diagnosis_f6871c95",
    "dob": "1974-04-01",
    "fullName": "Recipient_b8c980",
    "gender": "Female",
    "hospitalId": "H-773",
    "organRequired": "Heart",
    "registeredAt": "2026-01-30T21:51:21.790728",
    "status": "active",
    "submissionType": "backend-api",
    "test_heart_ct": "3",
    "test_heart_ct_date": "2026-01-09",
    "test_heart_echo": "4",
    "test_heart_echo_date": "2026-01-19",
    "test_heart_pftsTest": "3",
    "test_heart_pftsTest_date": "2026-01-24",
    "test_heart_xray": "10",
    "test_heart_xray_date": "2026-01-11",
    "urgencyStatus": "Moderate"
  },
  {
    "abhaId": "11448814607793",
    "bloodGroup": "B+",
    "diagnosis": "Diagnosis_6a852e7f",
    "dob": "1983-01-12",
    "fullName": "Recipient_7417a0",
    "gender": "Female",
    "hospitalId": "H-336",
    "organRequired": "Liver",
    "registeredAt": "2026-01-30T21:51:21.790754",
    "status": "active",
    "submissionType": "backend-api",
    "test_liver_ct": "4",
    "test_liver_ct_date": "2026-01-24",
    "test_liver_echo": "3",
    "test_liver_echo_date": "2026-01-01",
    "test_liver_pftsTest": "5",
    "test_liver_pftsTest_date": "2025-12-31",
    "test_liver_xray": "5",
    "test_liver_xray_date": "2026-01-27",
    "urgencyStatus": "Critical (ICU)"
  },
  {
    "abhaId": "62236728110901",
    "bloodGroup": "A+",
    "diagnosis": "Diagnosis_f30509d2",
    "dob": "1982-09-17",
    "fullName": "Recipient_fbb40d",
    "gender": "Male",
    "hospitalId": "H-848",
    "organRequired": "Lungs",
    "registeredAt": "2026-01-30T21:51:21.790782",
    "status": "active",
    "submissionType": "backend-api",
    "test_lungs_ct": "9",
    "test_lungs_ct_date": "2026-01-12",
    "test_lungs_echo": "10",
    "test_lungs_echo_date": "2026-01-28",
    "test_lungs_pftsTest": "4",
    "test_lungs_pftsTest_date": "2026-01-18",
    "test_lungs_xray": "1",
    "test_lungs_xray_date": "2026-01-18",
    "urgencyStatus": "Critical (ICU)"
  },
  {
    "abhaId": "45610659600404",
    "bloodGroup": "AB-",
    "diagnosis": "Diagnosis_8699235a",
    "dob": "1984-04-30",
    "fullName": "Recipient_c85ae3",
    "gender": "Male",
    "hospitalId": "H-472",
    "organRequired": "Heart",
    "registeredAt": "2026-01-30T21:51:21.790815",
    "status": "active",
    "submissionType": "backend-api",
    "test_heart_ct": "7",
    "test_heart_ct_date": "2026-01-08",
    "test_heart_echo": "6",
    "test_heart_echo_date": "2026-01-16",
    "test_heart_pftsTest": "7",
    "test_heart_pftsTest_date": "2026-01-25",
    "test_heart_xray": "3",
    "test_heart_xray_date": "2026-01-04",
    "urgencyStatus": "Stable"
  },
  {
    "abhaId": "27786632849905",
    "bloodGroup": "B+",
    "diagnosis": "Diagnosis_1a293658",
    "dob": "1981-03-26",
    "fullName": "Recipient_f98144",
    "gender": "Female",
    "hospitalId": "H-992",
    "organRequired": "Lungs",
    "registeredAt": "2026-01-30T21:51:21.790847",
    "status": "active",
    "submissionType": "backend-api",
    "test_lungs_ct": "2",
    "test_lungs_ct_date": "2026-01-11",
    "test_lungs_echo": "9",
    "test_lungs_echo_date": "2026-01-13",
    "test_lungs_pftsTest": "7",
    "test_lungs_pftsTest_date": "2026-01-08",
    "test_lungs_xray": "7",
    "test_lungs_xray_date": "2026-01-05",
    "urgencyStatus": "Stable"
  },
  {
    "abhaId": "28484808402250",
    "bloodGroup": "B+",
    "diagnosis": "Diagnosis_7efb4290",
    "dob": "2008-11-26",
    "fullName": "Recipient_a16fb7",
    "gender": "Female",
    "hospitalId": "H-563",
    "organRequired": "Heart",
    "registeredAt": "2026-01-30T21:51:21.790874",
    "status": "active",
    "submissionType": "backend-api",
    "test_heart_ct": "10",
    "test_heart_ct_date": "2026-01-17",
    "test_heart_echo": "5",
    "test_heart_echo_date": "2026-01-14",
    "test_heart_pftsTest": "9",
    "test_heart_pftsTest_date": "2026-01-29",
    "test_heart_xray": "9",
    "test_heart_xray_date": "2026-01-15",
    "urgencyStatus": "Stable"
  },
  {
    "abhaId": "71836526699574",
    "bloodGroup": "O-",
    "diagnosis": "Diagnosis_3c3e2e94",
    "dob": "1968-11-19",
    "fullName": "Recipient_f23cd2",
    "gender": "Female",
    "hospitalId": "H-917",
    "organRequired": "Kidney",
    "registeredAt": "2026-01-30T21:51:21.790901",
    "status": "active",
    "submissionType": "backend-api",
    "test_kidney_ct": "5",
    "test_kidney_ct_date": "2026-01-11",
    "test_kidney_echo": "2",
    "test_kidney_echo_date": "2026-01-08",
    "test_kidney_pftsTest": "6",
    "test_kidney_pftsTest_date": "2026-01-15",
    "test_kidney_xray": "4",
    "test_kidney_xray_date": "2026-01-29",
    "urgencyStatus": "Moderate"
  },
  {
    "abhaId": "39516884783785",
    "bloodGroup": "A-",
    "diagnosis": "Diagnosis_9cfc3966",
    "dob": "1964-06-16",
    "fullName": "Recipient_f28b7f",
    "gender": "Male",
    "hospitalId": "H-674",
    "organRequired": "Kidney",
    "registeredAt": "2026-01-30T21:51:21.790930",
    "status": "active",
    "submissionType": "backend-api",
    "test_kidney_ct": "10",
    "test_kidney_ct_date": "2026-01-04",
    "test_kidney_echo": "1",
    "test_kidney_echo_date": "2026-01-13",
    "test_kidney_pftsTest": "3",
    "test_kidney_pftsTest_date": "2026-01-13",
    "test_kidney_xray": "1",
    "test_kidney_xray_date": "2026-01-20",
    "urgencyStatus": "Moderate"
  },
  {
    "abhaId": "70163051444708",
    "bloodGroup": "A-",
    "diagnosis": "Diagnosis_3d79c811",
    "dob": "1985-06-12",
    "fullName": "Recipient_4e05d3",
    "gender": "Male",
    "hospitalId": "H-309",
    "organRequired": "Kidney",
    "registeredAt": "2026-01-30T21:51:21.790959",
    "status": "active",
    "submissionType": "backend-api",
    "test_kidney_ct": "4",
    "test_kidney_ct_date": "2026-01-09",
    "test_kidney_echo": "7",
    "test_kidney_echo_date": "2026-01-28",
    "test_kidney_pftsTest": "6",
    "test_kidney_pftsTest_date": "2026-01-14",
    "test_kidney_xray": "3",
    "test_kidney_xray_date": "2026-01-23",
    "urgencyStatus": "Critical (ICU)"
  },
  {
    "abhaId": "15580971984465",
    "bloodGroup": "O+",
    "diagnosis": "Diagnosis_ad5bf3ca",
    "dob": "2004-07-17",
    "fullName": "Recipient_577923",
    "gender": "Female",
    "hospitalId": "H-753",
    "organRequired": "Kidney",
    "registeredAt": "2026-01-30T21:51:21.790988",
    "status": "active",
    "submissionType": "backend-api",
    "test_kidney_ct": "7",
    "test_kidney_ct_date": "2026-01-15",
    "test_kidney_echo": "7",
    "test_kidney_echo_date": "2026-01-09",
    "test_kidney_pftsTest": "10",
    "test_kidney_pftsTest_date": "2026-01-24",
    "test_kidney_xray": "2",
    "test_kidney_xray_date": "2026-01-28",
    "urgencyStatus": "Urgent (Hospitalized)"
  },
  {
    "abhaId": "69735461950368",
    "bloodGroup": "B+",
    "diagnosis": "Diagnosis_1b1c3232",
    "dob": "1992-03-29",
    "fullName": "Recipient_f13b6c",
    "gender": "Male",
    "hospitalId": "H-197",
    "organRequired": "Lungs",
    "registeredAt": "2026-01-30T21:51:21.791017",
    "status": "active",
    "submissionType": "backend-api",
    "test_lungs_ct": "1",
    "test_lungs_ct_date": "2026-01-28",
    "test_lungs_echo": "8",
    "test_lungs_echo_date": "2026-01-06",
    "test_lungs_pftsTest": "2",
    "test_lungs_pftsTest_date": "2026-01-12",
    "test_lungs_xray": "5",
    "test_lungs_xray_date": "2026-01-03",
    "urgencyStatus": "Stable"
  },
  {
    "abhaId": "54189912909772",
    "bloodGroup": "AB-",
    "diagnosis": "Diagnosis_7a26e4dc",
    "dob": "1997-08-24",
    "fullName": "Recipient_5939d1",
    "gender": "Female",
    "hospitalId": "H-150",
    "organRequired": "Lungs",
    "registeredAt": "2026-01-30T21:51:21.791046",
    "status": "active",
    "submissionType": "backend-api",
    "test_lungs_ct": "6",
    "test_lungs_ct_date": "2026-01-08",
    "test_lungs_echo": "4",
    "test_lungs_echo_date": "2026-01-02",
    "test_lungs_pftsTest": "5",
    "test_lungs_pftsTest_date": "2026-01-18",
    "test_lungs_xray": "3",
    "test_lungs_xray_date": "2026-01-20",
    "urgencyStatus": "Moderate"
  },
  {
    "abhaId": "28402619128712",
    "bloodGroup": "AB+",
    "diagnosis": "Diagnosis_a1fbc0a4",
    "dob": "1998-03-22",
    "fullName": "Recipient_21b1c3",
    "gender": "Male",
    "hospitalId": "H-882",
    "organRequired": "Kidney",
    "registeredAt": "2026-01-30T21:51:21.791076",
    "status": "active",
    "submissionType": "backend-api",
    "test_kidney_ct": "10",
    "test_kidney_ct_date": "2026-01-08",
    "test_kidney_echo": "1",
    "test_kidney_echo_date": "2026-01-23",
    "test_kidney_pftsTest": "6",
    "test_kidney_pftsTest_date": "2026-01-12",
    "test_kidney_xray": "8",
    "test_kidney_xray_date": "2026-01-14",
    "urgencyStatus": "Critical (ICU)"
  },
  {
    "abhaId": "32614287549635",
    "bloodGroup": "O-",
    "diagnosis": "Diagnosis_eefacd44",
    "dob": "1998-05-09",
    "fullName": "Recipient_c6c641",
    "gender": "Female",
    "hospitalId": "H-565",
    "organRequired": "Heart",
    "registeredAt": "2026-01-30T21:51:21.791104",
    "status": "active",
    "submissionType": "backend-api",
    "test_heart_ct": "2",
    "test_heart_ct_date": "2026-01-17",
    "test_heart_echo": "1",
    "test_heart_echo_date": "2026-01-17",
    "test_heart_pftsTest": "2",
    "test_heart_pftsTest_date": "2025-12-31",
    "test_heart_xray": "7",
    "test_heart_xray_date": "2026-01-25",
    "urgencyStatus": "Urgent (Hospitalized)"
  },
  {
    "abhaId": "74590962976669",
    "bloodGroup": "B+",
    "diagnosis": "Diagnosis_7c615da5",
    "dob": "1966-10-15",
    "fullName": "Recipient_2c3ac1",
    "gender": "Female",
    "hospitalId": "H-364",
    "organRequired": "Kidney",
    "registeredAt": "2026-01-30T21:51:21.791132",
    "status": "active",
    "submissionType": "backend-api",
    "test_kidney_ct": "9",
    "test_kidney_ct_date": "2026-01-11",
    "test_kidney_echo": "2",
    "test_kidney_echo_date": "2026-01-08",
    "test_kidney_pftsTest": "1",
    "test_kidney_pftsTest_date": "2026-01-22",
    "test_kidney_xray": "5",
    "test_kidney_xray_date": "2026-01-25",
    "urgencyStatus": "Critical (ICU)"
  },
  {
    "abhaId": "97813739258988",
    "bloodGroup": "A-",
    "diagnosis": "Diagnosis_389cff04",
    "dob": "1988-02-27",
    "fullName": "Recipient_a95957",
    "gender": "Male",
    "hospitalId": "H-184",
    "organRequired": "Heart",
    "registeredAt": "2026-01-30T21:51:21.791158",
    "status": "active",
    "submissionType": "backend-api",
    "test_heart_ct": "10",
    "test_heart_ct_date": "2026-01-19",
    "test_heart_echo": "9",
    "test_heart_echo_date": "2026-01-19",
    "test_heart_pftsTest": "6",
    "test_heart_pftsTest_date": "2026-01-07",
    "test_heart_xray": "5",
    "test_heart_xray_date": "2026-01-18",
    "urgencyStatus": "Moderate"
  },
  {
    "abhaId": "18770260589620",
    "bloodGroup": "O-",
    "diagnosis": "Diagnosis_b75075c4",
    "dob": "1967-01-11",
    "fullName": "Recipient_3377bc",
    "gender": "Male",
    "hospitalId": "H-388",
    "organRequired": "Lungs",
    "registeredAt": "2026-01-30T21:51:21.791185",
    "status": "active",
    "submissionType": "backend-api",
    "test_lungs_ct": "5",
    "test_lungs_ct_date": "2026-01-17",
    "test_lungs_echo": "5",
    "test_lungs_echo_date": "2026-01-05",
    "test_lungs_pftsTest": "1",
    "test_lungs_pftsTest_date": "2026-01-04",
    "test_lungs_xray": "8",
    "test_lungs_xray_date": "2026-01-16",
    "urgencyStatus": "Critical (ICU)"
  },
  {
    "abhaId": "60848504056728",
    "bloodGroup": "B-",
    "diagnosis": "Diagnosis_90690f81",
    "dob": "2006-12-30",
    "fullName": "Recipient_e21022",
    "gender": "Female",
    "hospitalId": "H-895",
    "organRequired": "Heart",
    "registeredAt": "2026-01-30T21:51:21.791222",
    "status": "active",
    "submissionType": "backend-api",
    "test_heart_ct": "9",
    "test_heart_ct_date": "2026-01-17",
    "test_heart_echo": "3",
    "test_heart_echo_date": "2026-01-01",
    "test_heart_pftsTest": "1",
    "test_heart_pftsTest_date": "2026-01-13",
    "test_heart_xray": "1",
    "test_heart_xray_date": "2026-01-12",
    "urgencyStatus": "Urgent (Hospitalized)"
  },
  {
    "abhaId": "60439859952586",
    "bloodGroup": "AB-",
    "diagnosis": "Diagnosis_ce0b187b",
    "dob": "1964-01-25",
    "fullName": "Recipient_424043",
    "gender": "Female",
    "hospitalId": "H-530",
    "organRequired": "Lungs",
    "registeredAt": "2026-01-30T21:51:21.791251",
    "status": "active",
    "submissionType": "backend-api",
    "test_lungs_ct": "4",
    "test_lungs_ct_date": "2026-01-29",
    "test_lungs_echo": "1",
    "test_lungs_echo_date": "2026-01-23",
    "test_lungs_pftsTest": "10",
    "test_lungs_pftsTest_date": "2026-01-06",
    "test_lungs_xray": "3",
    "test_lungs_xray_date": "2026-01-12",
    "urgencyStatus": "Stable"
  },
  {
    "abhaId": "39037910505724",
    "bloodGroup": "A-",
    "diagnosis": "Diagnosis_d1b75e64",
    "dob": "2004-04-19",
    "fullName": "Recipient_34899e",
    "gender": "Female",
    "hospitalId": "H-987",
    "organRequired": "Kidney",
    "registeredAt": "2026-01-30T21:51:21.791278",
    "status": "active",
    "submissionType": "backend-api",
    "test_kidney_ct": "7",
    "test_kidney_ct_date": "2026-01-04",
    "test_kidney_echo": "4",
    "test_kidney_echo_date": "2026-01-14",
    "test_kidney_pftsTest": "9",
    "test_kidney_pftsTest_date": "2026-01-29",
    "test_kidney_xray": "4",
    "test_kidney_xray_date": "2026-01-26",
    "urgencyStatus": "Urgent (Hospitalized)"
  },
  {
    "abhaId": "49128562351309",
    "bloodGroup": "A-",
    "diagnosis": "Diagnosis_751067b4",
    "dob": "1979-07-01",
    "fullName": "Recipient_bed8f9",
    "gender": "Male",
    "hospitalId": "H-214",
    "organRequired": "Heart",
    "registeredAt": "2026-01-30T21:51:21.791304",
    "status": "active",
    "submissionType": "backend-api",
    "test_heart_ct": "1",
    "test_heart_ct_date": "2026-01-11",
    "test_heart_echo": "4",
    "test_heart_echo_date": "2026-01-23",
    "test_heart_pftsTest": "4",
    "test_heart_pftsTest_date": "2025-12-31",
    "test_heart_xray": "1",
    "test_heart_xray_date": "2026-01-11",
    "urgencyStatus": "Moderate"
  },
  {
    "abhaId": "90884448655268",
    "bloodGroup": "B+",
    "diagnosis": "Diagnosis_420e1730",
    "dob": "1978-02-26",
    "fullName": "Recipient_cd0a8a",
    "gender": "Male",
    "hospitalId": "H-660",
    "organRequired": "Liver",
    "registeredAt": "2026-01-30T21:51:21.791330",
    "status": "active",
    "submissionType": "backend-api",
    "test_liver_ct": "5",
    "test_liver_ct_date": "2026-01-27",
    "test_liver_echo": "7",
    "test_liver_echo_date": "2026-01-05",
    "test_liver_pftsTest": "6",
    "test_liver_pftsTest_date": "2026-01-05",
    "test_liver_xray": "3",
    "test_liver_xray_date": "2026-01-08",
    "urgencyStatus": "Stable"
  },
  {
    "abhaId": "52296886201542",
    "bloodGroup": "A+",
    "diagnosis": "Diagnosis_bbbe88b9",
    "dob": "1976-10-22",
    "fullName": "Recipient_ecbf6e",
    "gender": "Female",
    "hospitalId": "H-602",
    "organRequired": "Liver",
    "registeredAt": "2026-01-30T21:51:21.791359",
    "status": "active",
    "submissionType": "backend-api",
    "test_liver_ct": "2",
    "test_liver_ct_date": "2026-01-20",
    "test_liver_echo": "7",
    "test_liver_echo_date": "2026-01-13",
    "test_liver_pftsTest": "9",
    "test_liver_pftsTest_date": "2026-01-11",
    "test_liver_xray": "1",
    "test_liver_xray_date": "2026-01-17",
    "urgencyStatus": "Stable"
  },
  {
    "abhaId": "76563007545705",
    "bloodGroup": "A-",
    "diagnosis": "Diagnosis_562a39c7",
    "dob": "1984-05-19",
    "fullName": "Recipient_47909f",
    "gender": "Male",
    "hospitalId": "H-449",
    "organRequired": "Heart",
    "registeredAt": "2026-01-30T21:51:21.791386",
    "status": "active",
    "submissionType": "backend-api",
    "test_heart_ct": "4",
    "test_heart_ct_date": "2026-01-09",
    "test_heart_echo": "1",
    "test_heart_echo_date": "2026-01-09",
    "test_heart_pftsTest": "6",
    "test_heart_pftsTest_date": "2026-01-14",
    "test_heart_xray": "1",
    "test_heart_xray_date": "2026-01-28",
    "urgencyStatus": "Stable"
  },
  {
    "abhaId": "35467244624572",
    "bloodGroup": "B-",
    "diagnosis": "Diagnosis_d4db7bd0",
    "dob": "1960-12-10",
    "fullName": "Recipient_46a9c2",
    "gender": "Male",
    "hospitalId": "H-231",
    "organRequired": "Kidney",
    "registeredAt": "2026-01-30T21:51:21.791412",
    "status": "active",
    "submissionType": "backend-api",
    "test_kidney_ct": "6",
    "test_kidney_ct_date": "2026-01-01",
    "test_kidney_echo": "2",
    "test_kidney_echo_date": "2026-01-20",
    "test_kidney_pftsTest": "8",
    "test_kidney_pftsTest_date": "2026-01-29",
    "test_kidney_xray": "5",
    "test_kidney_xray_date": "2026-01-05",
    "urgencyStatus": "Urgent (Hospitalized)"
  },
  {
    "abhaId": "51901908595624",
    "bloodGroup": "O+",
    "diagnosis": "Diagnosis_287d56f8",
    "dob": "2002-08-17",
    "fullName": "Recipient_65f34f",
    "gender": "Male",
    "hospitalId": "H-291",
    "organRequired": "Liver",
    "registeredAt": "2026-01-30T21:51:21.791440",
    "status": "active",
    "submissionType": "backend-api",
    "test_liver_ct": "6",
    "test_liver_ct_date": "2026-01-23",
    "test_liver_echo": "1",
    "test_liver_echo_date": "2026-01-25",
    "test_liver_pftsTest": "6",
    "test_liver_pftsTest_date": "2026-01-03",
    "test_liver_xray": "10",
    "test_liver_xray_date": "2026-01-15",
    "urgencyStatus": "Urgent (Hospitalized)"
  }
]